pybrid/base/analog/__init__.py
pybrid/base/analog/computations.py
pybrid/base/hybrid/__init__.py
pybrid/base/hybrid/computer.py
pybrid/base/hybrid/controller.py
pybrid/base/hybrid/elements.py
pybrid/base/hybrid/entities.py
pybrid/base/hybrid/exceptions.py
pybrid/base/hybrid/modules.py
pybrid/base/hybrid/programs/__init__.py
pybrid/base/hybrid/programs/base.py
pybrid/base/hybrid/programs/recl.py
pybrid/base/hybrid/programs/simple_run.py
pybrid/base/hybrid/protocol.py
pybrid/base/hybrid/run.py
pybrid/base/hybrid/utils.py
pybrid/base/transport/__init__.py
pybrid/base/transport/base.py
pybrid/base/transport/network.py
pybrid/base/transport/passthrough.py
pybrid/base/transport/serial.py
pybrid/base/transport/unix.py
pybrid/base/utils/__init__.py
pybrid/base/utils/collections.py
pybrid/base/utils/descriptors.py
pybrid/base/utils/imports.py
pybrid/base/utils/json.py
pybrid/base/utils/logging.py
pybrid/cli/base/__init__.py
pybrid/cli/base/__main__.py
pybrid/cli/base/base.py
pybrid/cli/base/commands.py
pybrid/cli/base/loader.py
pybrid/cli/base/ressources.py
pybrid/cli/base/shell.py
pybrid_computing_base-0.10.1.dist-info/METADATA
pybrid_computing_base-0.10.1.dist-info/WHEEL
pybrid_computing_base-0.10.1.dist-info/entry_points.txt
pybrid_computing_base-0.10.1.dist-info/RECORD
